Workbook

Sheet 1. Entrada
A1: CUENTA DE RESULTADOS DE BOLSILLO · ENTRADA
A2: Complemento de farmapro Impulso, edición 28 · La rentabilidad oculta. Rellena solo las celdas amarillas, una fila por mes. Todo lo demás se calcula en la hoja "2. Ratios".
B4: VENTAS POR FAMILIA (€) | H4: COSTE DE ESA VENTA POR FAMILIA (€) | N4: PERSONAL Y GASTOS FIJOS (€) | P4: STOCK A PRECIO DE COSTE POR FAMILIA (€) | V4: DESFASE DE CAJA (DÍAS)
A5: Mes | B5: Receta | C5: OTC | D5: Dermocosmética | E5: Nutrición | F5: Ortopedia | G5: Otros | H5: Receta | I5: OTC | J5: Dermocosmética | K5: Nutrición | L5: Ortopedia | M5: Otros | N5: Coste de personal (€) | O5: Gastos fijos totales del mes (€) | P5: Receta | Q5: OTC | R5: Dermocosmética | S5: Nutrición | T5: Ortopedia | U5: Otros | V5: Días de cobro (receta) | W5: Días de pago (mayorista)
A6: Enero
A7: Febrero
A8: Marzo
A9: Abril
A10: Mayo
A11: Junio
A12: Julio
A13: Agosto
A14: Septiembre
A15: Octubre
A16: Noviembre
A17: Diciembre
A19: Amarillo = celda de entrada (la rellenas tú). Blanco = se calcula sola en la hoja "2. Ratios". El coste de personal va aparte de gastos fijos porque el ratio 2 lo necesita solo: son los salarios más la Seguridad Social a cargo de la empresa, incluido tu propio coste si estás en el mostrador. Gastos fijos totales SÍ incluye el personal (alquiler, suministros, personal, cuotas...): es el que hace falta para el punto muerto.

Sheet 2. Ratios
A1: LOS CINCO RATIOS · CALCULADO SOLO
A2: Se calcula entero desde "1. Entrada". El color de cada celda te compara con tus propios doce meses, nunca con datos de fuera.
B4: MARGEN BRUTO POR FAMILIA (%) | H4: PESO SOBRE VENTA TOTAL (%) | N4: RATIOS 1B Y 2 · GLOBAL | P4: COBERTURA DE STOCK POR FAMILIA (DÍAS) | V4: RATIOS 3B, 4 Y 5 · GLOBAL
A5: Mes | B5: Receta | C5: OTC | D5: Dermocosmética | E5: Nutrición | F5: Ortopedia | G5: Otros | H5: Receta | I5: OTC | J5: Dermocosmética | K5: Nutrición | L5: Ortopedia | M5: Otros | N5: Margen bruto global | O5: Personal / margen bruto | P5: Receta | Q5: OTC | R5: Dermocosmética | S5: Nutrición | T5: Ortopedia | U5: Otros | V5: Cobertura stock global | W5: Punto muerto del mes (€) | X5: Desfase de caja (días)
A6: ='1. Entrada'!A6 | B6: =IFERROR(('1. Entrada'!B6-'1. Entrada'!H6)/'1. Entrada'!B6,"") | C6: =IFERROR(('1. Entrada'!C6-'1. Entrada'!I6)/'1. Entrada'!C6,"") | D6: =IFERROR(('1. Entrada'!D6-'1. Entrada'!J6)/'1. Entrada'!D6,"") | E6: =IFERROR(('1. Entrada'!E6-'1. Entrada'!K6)/'1. Entrada'!E6,"") | F6: =IFERROR(('1. Entrada'!F6-'1. Entrada'!L6)/'1. Entrada'!F6,"") | G6: =IFERROR(('1. Entrada'!G6-'1. Entrada'!M6)/'1. Entrada'!G6,"") | H6: =IFERROR('1. Entrada'!B6/(SUM('1. Entrada'!B6:G6)),"") | I6: =IFERROR('1. Entrada'!C6/(SUM('1. Entrada'!B6:G6)),"") | J6: =IFERROR('1. Entrada'!D6/(SUM('1. Entrada'!B6:G6)),"") | K6: =IFERROR('1. Entrada'!E6/(SUM('1. Entrada'!B6:G6)),"") | L6: =IFERROR('1. Entrada'!F6/(SUM('1. Entrada'!B6:G6)),"") | M6: =IFERROR('1. Entrada'!G6/(SUM('1. Entrada'!B6:G6)),"") | N6: =IFERROR(((SUM('1. Entrada'!B6:G6))-(SUM('1. Entrada'!H6:M6)))/(SUM('1. Entrada'!B6:G6)),"") | O6: =IFERROR('1. Entrada'!N6/((SUM('1. Entrada'!B6:G6))-(SUM('1. Entrada'!H6:M6))),"") | P6: =IFERROR('1. Entrada'!P6/'1. Entrada'!H6*30,"") | Q6: =IFERROR('1. Entrada'!Q6/'1. Entrada'!I6*30,"") | R6: =IFERROR('1. Entrada'!R6/'1. Entrada'!J6*30,"") | S6: =IFERROR('1. Entrada'!S6/'1. Entrada'!K6*30,"") | T6: =IFERROR('1. Entrada'!T6/'1. Entrada'!L6*30,"") | U6: =IFERROR('1. Entrada'!U6/'1. Entrada'!M6*30,"") | V6: =IFERROR((SUM('1. Entrada'!P6:U6))/(SUM('1. Entrada'!H6:M6))*30,"") | W6: =IFERROR('1. Entrada'!O6/(((SUM('1. Entrada'!B6:G6))-(SUM('1. Entrada'!H6:M6)))/(SUM('1. Entrada'!B6:G6))),"") | X6: =IF(OR('1. Entrada'!V6="",'1. Entrada'!W6=""),"",'1. Entrada'!V6-'1. Entrada'!W6)
A7: ='1. Entrada'!A7 | B7: =IFERROR(('1. Entrada'!B7-'1. Entrada'!H7)/'1. Entrada'!B7,"") | C7: =IFERROR(('1. Entrada'!C7-'1. Entrada'!I7)/'1. Entrada'!C7,"") | D7: =IFERROR(('1. Entrada'!D7-'1. Entrada'!J7)/'1. Entrada'!D7,"") | E7: =IFERROR(('1. Entrada'!E7-'1. Entrada'!K7)/'1. Entrada'!E7,"") | F7: =IFERROR(('1. Entrada'!F7-'1. Entrada'!L7)/'1. Entrada'!F7,"") | G7: =IFERROR(('1. Entrada'!G7-'1. Entrada'!M7)/'1. Entrada'!G7,"") | H7: =IFERROR('1. Entrada'!B7/(SUM('1. Entrada'!B7:G7)),"") | I7: =IFERROR('1. Entrada'!C7/(SUM('1. Entrada'!B7:G7)),"") | J7: =IFERROR('1. Entrada'!D7/(SUM('1. Entrada'!B7:G7)),"") | K7: =IFERROR('1. Entrada'!E7/(SUM('1. Entrada'!B7:G7)),"") | L7: =IFERROR('1. Entrada'!F7/(SUM('1. Entrada'!B7:G7)),"") | M7: =IFERROR('1. Entrada'!G7/(SUM('1. Entrada'!B7:G7)),"") | N7: =IFERROR(((SUM('1. Entrada'!B7:G7))-(SUM('1. Entrada'!H7:M7)))/(SUM('1. Entrada'!B7:G7)),"") | O7: =IFERROR('1. Entrada'!N7/((SUM('1. Entrada'!B7:G7))-(SUM('1. Entrada'!H7:M7))),"") | P7: =IFERROR('1. Entrada'!P7/'1. Entrada'!H7*30,"") | Q7: =IFERROR('1. Entrada'!Q7/'1. Entrada'!I7*30,"") | R7: =IFERROR('1. Entrada'!R7/'1. Entrada'!J7*30,"") | S7: =IFERROR('1. Entrada'!S7/'1. Entrada'!K7*30,"") | T7: =IFERROR('1. Entrada'!T7/'1. Entrada'!L7*30,"") | U7: =IFERROR('1. Entrada'!U7/'1. Entrada'!M7*30,"") | V7: =IFERROR((SUM('1. Entrada'!P7:U7))/(SUM('1. Entrada'!H7:M7))*30,"") | W7: =IFERROR('1. Entrada'!O7/(((SUM('1. Entrada'!B7:G7))-(SUM('1. Entrada'!H7:M7)))/(SUM('1. Entrada'!B7:G7))),"") | X7: =IF(OR('1. Entrada'!V7="",'1. Entrada'!W7=""),"",'1. Entrada'!V7-'1. Entrada'!W7)
A8: ='1. Entrada'!A8 | B8: =IFERROR(('1. Entrada'!B8-'1. Entrada'!H8)/'1. Entrada'!B8,"") | C8: =IFERROR(('1. Entrada'!C8-'1. Entrada'!I8)/'1. Entrada'!C8,"") | D8: =IFERROR(('1. Entrada'!D8-'1. Entrada'!J8)/'1. Entrada'!D8,"") | E8: =IFERROR(('1. Entrada'!E8-'1. Entrada'!K8)/'1. Entrada'!E8,"") | F8: =IFERROR(('1. Entrada'!F8-'1. Entrada'!L8)/'1. Entrada'!F8,"") | G8: =IFERROR(('1. Entrada'!G8-'1. Entrada'!M8)/'1. Entrada'!G8,"") | H8: =IFERROR('1. Entrada'!B8/(SUM('1. Entrada'!B8:G8)),"") | I8: =IFERROR('1. Entrada'!C8/(SUM('1. Entrada'!B8:G8)),"") | J8: =IFERROR('1. Entrada'!D8/(SUM('1. Entrada'!B8:G8)),"") | K8: =IFERROR('1. Entrada'!E8/(SUM('1. Entrada'!B8:G8)),"") | L8: =IFERROR('1. Entrada'!F8/(SUM('1. Entrada'!B8:G8)),"") | M8: =IFERROR('1. Entrada'!G8/(SUM('1. Entrada'!B8:G8)),"") | N8: =IFERROR(((SUM('1. Entrada'!B8:G8))-(SUM('1. Entrada'!H8:M8)))/(SUM('1. Entrada'!B8:G8)),"") | O8: =IFERROR('1. Entrada'!N8/((SUM('1. Entrada'!B8:G8))-(SUM('1. Entrada'!H8:M8))),"") | P8: =IFERROR('1. Entrada'!P8/'1. Entrada'!H8*30,"") | Q8: =IFERROR('1. Entrada'!Q8/'1. Entrada'!I8*30,"") | R8: =IFERROR('1. Entrada'!R8/'1. Entrada'!J8*30,"") | S8: =IFERROR('1. Entrada'!S8/'1. Entrada'!K8*30,"") | T8: =IFERROR('1. Entrada'!T8/'1. Entrada'!L8*30,"") | U8: =IFERROR('1. Entrada'!U8/'1. Entrada'!M8*30,"") | V8: =IFERROR((SUM('1. Entrada'!P8:U8))/(SUM('1. Entrada'!H8:M8))*30,"") | W8: =IFERROR('1. Entrada'!O8/(((SUM('1. Entrada'!B8:G8))-(SUM('1. Entrada'!H8:M8)))/(SUM('1. Entrada'!B8:G8))),"") | X8: =IF(OR('1. Entrada'!V8="",'1. Entrada'!W8=""),"",'1. Entrada'!V8-'1. Entrada'!W8)
A9: ='1. Entrada'!A9 | B9: =IFERROR(('1. Entrada'!B9-'1. Entrada'!H9)/'1. Entrada'!B9,"") | C9: =IFERROR(('1. Entrada'!C9-'1. Entrada'!I9)/'1. Entrada'!C9,"") | D9: =IFERROR(('1. Entrada'!D9-'1. Entrada'!J9)/'1. Entrada'!D9,"") | E9: =IFERROR(('1. Entrada'!E9-'1. Entrada'!K9)/'1. Entrada'!E9,"") | F9: =IFERROR(('1. Entrada'!F9-'1. Entrada'!L9)/'1. Entrada'!F9,"") | G9: =IFERROR(('1. Entrada'!G9-'1. Entrada'!M9)/'1. Entrada'!G9,"") | H9: =IFERROR('1. Entrada'!B9/(SUM('1. Entrada'!B9:G9)),"") | I9: =IFERROR('1. Entrada'!C9/(SUM('1. Entrada'!B9:G9)),"") | J9: =IFERROR('1. Entrada'!D9/(SUM('1. Entrada'!B9:G9)),"") | K9: =IFERROR('1. Entrada'!E9/(SUM('1. Entrada'!B9:G9)),"") | L9: =IFERROR('1. Entrada'!F9/(SUM('1. Entrada'!B9:G9)),"") | M9: =IFERROR('1. Entrada'!G9/(SUM('1. Entrada'!B9:G9)),"") | N9: =IFERROR(((SUM('1. Entrada'!B9:G9))-(SUM('1. Entrada'!H9:M9)))/(SUM('1. Entrada'!B9:G9)),"") | O9: =IFERROR('1. Entrada'!N9/((SUM('1. Entrada'!B9:G9))-(SUM('1. Entrada'!H9:M9))),"") | P9: =IFERROR('1. Entrada'!P9/'1. Entrada'!H9*30,"") | Q9: =IFERROR('1. Entrada'!Q9/'1. Entrada'!I9*30,"") | R9: =IFERROR('1. Entrada'!R9/'1. Entrada'!J9*30,"") | S9: =IFERROR('1. Entrada'!S9/'1. Entrada'!K9*30,"") | T9: =IFERROR('1. Entrada'!T9/'1. Entrada'!L9*30,"") | U9: =IFERROR('1. Entrada'!U9/'1. Entrada'!M9*30,"") | V9: =IFERROR((SUM('1. Entrada'!P9:U9))/(SUM('1. Entrada'!H9:M9))*30,"") | W9: =IFERROR('1. Entrada'!O9/(((SUM('1. Entrada'!B9:G9))-(SUM('1. Entrada'!H9:M9)))/(SUM('1. Entrada'!B9:G9))),"") | X9: =IF(OR('1. Entrada'!V9="",'1. Entrada'!W9=""),"",'1. Entrada'!V9-'1. Entrada'!W9)
A10: ='1. Entrada'!A10 | B10: =IFERROR(('1. Entrada'!B10-'1. Entrada'!H10)/'1. Entrada'!B10,"") | C10: =IFERROR(('1. Entrada'!C10-'1. Entrada'!I10)/'1. Entrada'!C10,"") | D10: =IFERROR(('1. Entrada'!D10-'1. Entrada'!J10)/'1. Entrada'!D10,"") | E10: =IFERROR(('1. Entrada'!E10-'1. Entrada'!K10)/'1. Entrada'!E10,"") | F10: =IFERROR(('1. Entrada'!F10-'1. Entrada'!L10)/'1. Entrada'!F10,"") | G10: =IFERROR(('1. Entrada'!G10-'1. Entrada'!M10)/'1. Entrada'!G10,"") | H10: =IFERROR('1. Entrada'!B10/(SUM('1. Entrada'!B10:G10)),"") | I10: =IFERROR('1. Entrada'!C10/(SUM('1. Entrada'!B10:G10)),"") | J10: =IFERROR('1. Entrada'!D10/(SUM('1. Entrada'!B10:G10)),"") | K10: =IFERROR('1. Entrada'!E10/(SUM('1. Entrada'!B10:G10)),"") | L10: =IFERROR('1. Entrada'!F10/(SUM('1. Entrada'!B10:G10)),"") | M10: =IFERROR('1. Entrada'!G10/(SUM('1. Entrada'!B10:G10)),"") | N10: =IFERROR(((SUM('1. Entrada'!B10:G10))-(SUM('1. Entrada'!H10:M10)))/(SUM('1. Entrada'!B10:G10)),"") | O10: =IFERROR('1. Entrada'!N10/((SUM('1. Entrada'!B10:G10))-(SUM('1. Entrada'!H10:M10))),"") | P10: =IFERROR('1. Entrada'!P10/'1. Entrada'!H10*30,"") | Q10: =IFERROR('1. Entrada'!Q10/'1. Entrada'!I10*30,"") | R10: =IFERROR('1. Entrada'!R10/'1. Entrada'!J10*30,"") | S10: =IFERROR('1. Entrada'!S10/'1. Entrada'!K10*30,"") | T10: =IFERROR('1. Entrada'!T10/'1. Entrada'!L10*30,"") | U10: =IFERROR('1. Entrada'!U10/'1. Entrada'!M10*30,"") | V10: =IFERROR((SUM('1. Entrada'!P10:U10))/(SUM('1. Entrada'!H10:M10))*30,"") | W10: =IFERROR('1. Entrada'!O10/(((SUM('1. Entrada'!B10:G10))-(SUM('1. Entrada'!H10:M10)))/(SUM('1. Entrada'!B10:G10))),"") | X10: =IF(OR('1. Entrada'!V10="",'1. Entrada'!W10=""),"",'1. Entrada'!V10-'1. Entrada'!W10)
A11: ='1. Entrada'!A11 | B11: =IFERROR(('1. Entrada'!B11-'1. Entrada'!H11)/'1. Entrada'!B11,"") | C11: =IFERROR(('1. Entrada'!C11-'1. Entrada'!I11)/'1. Entrada'!C11,"") | D11: =IFERROR(('1. Entrada'!D11-'1. Entrada'!J11)/'1. Entrada'!D11,"") | E11: =IFERROR(('1. Entrada'!E11-'1. Entrada'!K11)/'1. Entrada'!E11,"") | F11: =IFERROR(('1. Entrada'!F11-'1. Entrada'!L11)/'1. Entrada'!F11,"") | G11: =IFERROR(('1. Entrada'!G11-'1. Entrada'!M11)/'1. Entrada'!G11,"") | H11: =IFERROR('1. Entrada'!B11/(SUM('1. Entrada'!B11:G11)),"") | I11: =IFERROR('1. Entrada'!C11/(SUM('1. Entrada'!B11:G11)),"") | J11: =IFERROR('1. Entrada'!D11/(SUM('1. Entrada'!B11:G11)),"") | K11: =IFERROR('1. Entrada'!E11/(SUM('1. Entrada'!B11:G11)),"") | L11: =IFERROR('1. Entrada'!F11/(SUM('1. Entrada'!B11:G11)),"") | M11: =IFERROR('1. Entrada'!G11/(SUM('1. Entrada'!B11:G11)),"") | N11: =IFERROR(((SUM('1. Entrada'!B11:G11))-(SUM('1. Entrada'!H11:M11)))/(SUM('1. Entrada'!B11:G11)),"") | O11: =IFERROR('1. Entrada'!N11/((SUM('1. Entrada'!B11:G11))-(SUM('1. Entrada'!H11:M11))),"") | P11: =IFERROR('1. Entrada'!P11/'1. Entrada'!H11*30,"") | Q11: =IFERROR('1. Entrada'!Q11/'1. Entrada'!I11*30,"") | R11: =IFERROR('1. Entrada'!R11/'1. Entrada'!J11*30,"") | S11: =IFERROR('1. Entrada'!S11/'1. Entrada'!K11*30,"") | T11: =IFERROR('1. Entrada'!T11/'1. Entrada'!L11*30,"") | U11: =IFERROR('1. Entrada'!U11/'1. Entrada'!M11*30,"") | V11: =IFERROR((SUM('1. Entrada'!P11:U11))/(SUM('1. Entrada'!H11:M11))*30,"") | W11: =IFERROR('1. Entrada'!O11/(((SUM('1. Entrada'!B11:G11))-(SUM('1. Entrada'!H11:M11)))/(SUM('1. Entrada'!B11:G11))),"") | X11: =IF(OR('1. Entrada'!V11="",'1. Entrada'!W11=""),"",'1. Entrada'!V11-'1. Entrada'!W11)
A12: ='1. Entrada'!A12 | B12: =IFERROR(('1. Entrada'!B12-'1. Entrada'!H12)/'1. Entrada'!B12,"") | C12: =IFERROR(('1. Entrada'!C12-'1. Entrada'!I12)/'1. Entrada'!C12,"") | D12: =IFERROR(('1. Entrada'!D12-'1. Entrada'!J12)/'1. Entrada'!D12,"") | E12: =IFERROR(('1. Entrada'!E12-'1. Entrada'!K12)/'1. Entrada'!E12,"") | F12: =IFERROR(('1. Entrada'!F12-'1. Entrada'!L12)/'1. Entrada'!F12,"") | G12: =IFERROR(('1. Entrada'!G12-'1. Entrada'!M12)/'1. Entrada'!G12,"") | H12: =IFERROR('1. Entrada'!B12/(SUM('1. Entrada'!B12:G12)),"") | I12: =IFERROR('1. Entrada'!C12/(SUM('1. Entrada'!B12:G12)),"") | J12: =IFERROR('1. Entrada'!D12/(SUM('1. Entrada'!B12:G12)),"") | K12: =IFERROR('1. Entrada'!E12/(SUM('1. Entrada'!B12:G12)),"") | L12: =IFERROR('1. Entrada'!F12/(SUM('1. Entrada'!B12:G12)),"") | M12: =IFERROR('1. Entrada'!G12/(SUM('1. Entrada'!B12:G12)),"") | N12: =IFERROR(((SUM('1. Entrada'!B12:G12))-(SUM('1. Entrada'!H12:M12)))/(SUM('1. Entrada'!B12:G12)),"") | O12: =IFERROR('1. Entrada'!N12/((SUM('1. Entrada'!B12:G12))-(SUM('1. Entrada'!H12:M12))),"") | P12: =IFERROR('1. Entrada'!P12/'1. Entrada'!H12*30,"") | Q12: =IFERROR('1. Entrada'!Q12/'1. Entrada'!I12*30,"") | R12: =IFERROR('1. Entrada'!R12/'1. Entrada'!J12*30,"") | S12: =IFERROR('1. Entrada'!S12/'1. Entrada'!K12*30,"") | T12: =IFERROR('1. Entrada'!T12/'1. Entrada'!L12*30,"") | U12: =IFERROR('1. Entrada'!U12/'1. Entrada'!M12*30,"") | V12: =IFERROR((SUM('1. Entrada'!P12:U12))/(SUM('1. Entrada'!H12:M12))*30,"") | W12: =IFERROR('1. Entrada'!O12/(((SUM('1. Entrada'!B12:G12))-(SUM('1. Entrada'!H12:M12)))/(SUM('1. Entrada'!B12:G12))),"") | X12: =IF(OR('1. Entrada'!V12="",'1. Entrada'!W12=""),"",'1. Entrada'!V12-'1. Entrada'!W12)
A13: ='1. Entrada'!A13 | B13: =IFERROR(('1. Entrada'!B13-'1. Entrada'!H13)/'1. Entrada'!B13,"") | C13: =IFERROR(('1. Entrada'!C13-'1. Entrada'!I13)/'1. Entrada'!C13,"") | D13: =IFERROR(('1. Entrada'!D13-'1. Entrada'!J13)/'1. Entrada'!D13,"") | E13: =IFERROR(('1. Entrada'!E13-'1. Entrada'!K13)/'1. Entrada'!E13,"") | F13: =IFERROR(('1. Entrada'!F13-'1. Entrada'!L13)/'1. Entrada'!F13,"") | G13: =IFERROR(('1. Entrada'!G13-'1. Entrada'!M13)/'1. Entrada'!G13,"") | H13: =IFERROR('1. Entrada'!B13/(SUM('1. Entrada'!B13:G13)),"") | I13: =IFERROR('1. Entrada'!C13/(SUM('1. Entrada'!B13:G13)),"") | J13: =IFERROR('1. Entrada'!D13/(SUM('1. Entrada'!B13:G13)),"") | K13: =IFERROR('1. Entrada'!E13/(SUM('1. Entrada'!B13:G13)),"") | L13: =IFERROR('1. Entrada'!F13/(SUM('1. Entrada'!B13:G13)),"") | M13: =IFERROR('1. Entrada'!G13/(SUM('1. Entrada'!B13:G13)),"") | N13: =IFERROR(((SUM('1. Entrada'!B13:G13))-(SUM('1. Entrada'!H13:M13)))/(SUM('1. Entrada'!B13:G13)),"") | O13: =IFERROR('1. Entrada'!N13/((SUM('1. Entrada'!B13:G13))-(SUM('1. Entrada'!H13:M13))),"") | P13: =IFERROR('1. Entrada'!P13/'1. Entrada'!H13*30,"") | Q13: =IFERROR('1. Entrada'!Q13/'1. Entrada'!I13*30,"") | R13: =IFERROR('1. Entrada'!R13/'1. Entrada'!J13*30,"") | S13: =IFERROR('1. Entrada'!S13/'1. Entrada'!K13*30,"") | T13: =IFERROR('1. Entrada'!T13/'1. Entrada'!L13*30,"") | U13: =IFERROR('1. Entrada'!U13/'1. Entrada'!M13*30,"") | V13: =IFERROR((SUM('1. Entrada'!P13:U13))/(SUM('1. Entrada'!H13:M13))*30,"") | W13: =IFERROR('1. Entrada'!O13/(((SUM('1. Entrada'!B13:G13))-(SUM('1. Entrada'!H13:M13)))/(SUM('1. Entrada'!B13:G13))),"") | X13: =IF(OR('1. Entrada'!V13="",'1. Entrada'!W13=""),"",'1. Entrada'!V13-'1. Entrada'!W13)
A14: ='1. Entrada'!A14 | B14: =IFERROR(('1. Entrada'!B14-'1. Entrada'!H14)/'1. Entrada'!B14,"") | C14: =IFERROR(('1. Entrada'!C14-'1. Entrada'!I14)/'1. Entrada'!C14,"") | D14: =IFERROR(('1. Entrada'!D14-'1. Entrada'!J14)/'1. Entrada'!D14,"") | E14: =IFERROR(('1. Entrada'!E14-'1. Entrada'!K14)/'1. Entrada'!E14,"") | F14: =IFERROR(('1. Entrada'!F14-'1. Entrada'!L14)/'1. Entrada'!F14,"") | G14: =IFERROR(('1. Entrada'!G14-'1. Entrada'!M14)/'1. Entrada'!G14,"") | H14: =IFERROR('1. Entrada'!B14/(SUM('1. Entrada'!B14:G14)),"") | I14: =IFERROR('1. Entrada'!C14/(SUM('1. Entrada'!B14:G14)),"") | J14: =IFERROR('1. Entrada'!D14/(SUM('1. Entrada'!B14:G14)),"") | K14: =IFERROR('1. Entrada'!E14/(SUM('1. Entrada'!B14:G14)),"") | L14: =IFERROR('1. Entrada'!F14/(SUM('1. Entrada'!B14:G14)),"") | M14: =IFERROR('1. Entrada'!G14/(SUM('1. Entrada'!B14:G14)),"") | N14: =IFERROR(((SUM('1. Entrada'!B14:G14))-(SUM('1. Entrada'!H14:M14)))/(SUM('1. Entrada'!B14:G14)),"") | O14: =IFERROR('1. Entrada'!N14/((SUM('1. Entrada'!B14:G14))-(SUM('1. Entrada'!H14:M14))),"") | P14: =IFERROR('1. Entrada'!P14/'1. Entrada'!H14*30,"") | Q14: =IFERROR('1. Entrada'!Q14/'1. Entrada'!I14*30,"") | R14: =IFERROR('1. Entrada'!R14/'1. Entrada'!J14*30,"") | S14: =IFERROR('1. Entrada'!S14/'1. Entrada'!K14*30,"") | T14: =IFERROR('1. Entrada'!T14/'1. Entrada'!L14*30,"") | U14: =IFERROR('1. Entrada'!U14/'1. Entrada'!M14*30,"") | V14: =IFERROR((SUM('1. Entrada'!P14:U14))/(SUM('1. Entrada'!H14:M14))*30,"") | W14: =IFERROR('1. Entrada'!O14/(((SUM('1. Entrada'!B14:G14))-(SUM('1. Entrada'!H14:M14)))/(SUM('1. Entrada'!B14:G14))),"") | X14: =IF(OR('1. Entrada'!V14="",'1. Entrada'!W14=""),"",'1. Entrada'!V14-'1. Entrada'!W14)
A15: ='1. Entrada'!A15 | B15: =IFERROR(('1. Entrada'!B15-'1. Entrada'!H15)/'1. Entrada'!B15,"") | C15: =IFERROR(('1. Entrada'!C15-'1. Entrada'!I15)/'1. Entrada'!C15,"") | D15: =IFERROR(('1. Entrada'!D15-'1. Entrada'!J15)/'1. Entrada'!D15,"") | E15: =IFERROR(('1. Entrada'!E15-'1. Entrada'!K15)/'1. Entrada'!E15,"") | F15: =IFERROR(('1. Entrada'!F15-'1. Entrada'!L15)/'1. Entrada'!F15,"") | G15: =IFERROR(('1. Entrada'!G15-'1. Entrada'!M15)/'1. Entrada'!G15,"") | H15: =IFERROR('1. Entrada'!B15/(SUM('1. Entrada'!B15:G15)),"") | I15: =IFERROR('1. Entrada'!C15/(SUM('1. Entrada'!B15:G15)),"") | J15: =IFERROR('1. Entrada'!D15/(SUM('1. Entrada'!B15:G15)),"") | K15: =IFERROR('1. Entrada'!E15/(SUM('1. Entrada'!B15:G15)),"") | L15: =IFERROR('1. Entrada'!F15/(SUM('1. Entrada'!B15:G15)),"") | M15: =IFERROR('1. Entrada'!G15/(SUM('1. Entrada'!B15:G15)),"") | N15: =IFERROR(((SUM('1. Entrada'!B15:G15))-(SUM('1. Entrada'!H15:M15)))/(SUM('1. Entrada'!B15:G15)),"") | O15: =IFERROR('1. Entrada'!N15/((SUM('1. Entrada'!B15:G15))-(SUM('1. Entrada'!H15:M15))),"") | P15: =IFERROR('1. Entrada'!P15/'1. Entrada'!H15*30,"") | Q15: =IFERROR('1. Entrada'!Q15/'1. Entrada'!I15*30,"") | R15: =IFERROR('1. Entrada'!R15/'1. Entrada'!J15*30,"") | S15: =IFERROR('1. Entrada'!S15/'1. Entrada'!K15*30,"") | T15: =IFERROR('1. Entrada'!T15/'1. Entrada'!L15*30,"") | U15: =IFERROR('1. Entrada'!U15/'1. Entrada'!M15*30,"") | V15: =IFERROR((SUM('1. Entrada'!P15:U15))/(SUM('1. Entrada'!H15:M15))*30,"") | W15: =IFERROR('1. Entrada'!O15/(((SUM('1. Entrada'!B15:G15))-(SUM('1. Entrada'!H15:M15)))/(SUM('1. Entrada'!B15:G15))),"") | X15: =IF(OR('1. Entrada'!V15="",'1. Entrada'!W15=""),"",'1. Entrada'!V15-'1. Entrada'!W15)
A16: ='1. Entrada'!A16 | B16: =IFERROR(('1. Entrada'!B16-'1. Entrada'!H16)/'1. Entrada'!B16,"") | C16: =IFERROR(('1. Entrada'!C16-'1. Entrada'!I16)/'1. Entrada'!C16,"") | D16: =IFERROR(('1. Entrada'!D16-'1. Entrada'!J16)/'1. Entrada'!D16,"") | E16: =IFERROR(('1. Entrada'!E16-'1. Entrada'!K16)/'1. Entrada'!E16,"") | F16: =IFERROR(('1. Entrada'!F16-'1. Entrada'!L16)/'1. Entrada'!F16,"") | G16: =IFERROR(('1. Entrada'!G16-'1. Entrada'!M16)/'1. Entrada'!G16,"") | H16: =IFERROR('1. Entrada'!B16/(SUM('1. Entrada'!B16:G16)),"") | I16: =IFERROR('1. Entrada'!C16/(SUM('1. Entrada'!B16:G16)),"") | J16: =IFERROR('1. Entrada'!D16/(SUM('1. Entrada'!B16:G16)),"") | K16: =IFERROR('1. Entrada'!E16/(SUM('1. Entrada'!B16:G16)),"") | L16: =IFERROR('1. Entrada'!F16/(SUM('1. Entrada'!B16:G16)),"") | M16: =IFERROR('1. Entrada'!G16/(SUM('1. Entrada'!B16:G16)),"") | N16: =IFERROR(((SUM('1. Entrada'!B16:G16))-(SUM('1. Entrada'!H16:M16)))/(SUM('1. Entrada'!B16:G16)),"") | O16: =IFERROR('1. Entrada'!N16/((SUM('1. Entrada'!B16:G16))-(SUM('1. Entrada'!H16:M16))),"") | P16: =IFERROR('1. Entrada'!P16/'1. Entrada'!H16*30,"") | Q16: =IFERROR('1. Entrada'!Q16/'1. Entrada'!I16*30,"") | R16: =IFERROR('1. Entrada'!R16/'1. Entrada'!J16*30,"") | S16: =IFERROR('1. Entrada'!S16/'1. Entrada'!K16*30,"") | T16: =IFERROR('1. Entrada'!T16/'1. Entrada'!L16*30,"") | U16: =IFERROR('1. Entrada'!U16/'1. Entrada'!M16*30,"") | V16: =IFERROR((SUM('1. Entrada'!P16:U16))/(SUM('1. Entrada'!H16:M16))*30,"") | W16: =IFERROR('1. Entrada'!O16/(((SUM('1. Entrada'!B16:G16))-(SUM('1. Entrada'!H16:M16)))/(SUM('1. Entrada'!B16:G16))),"") | X16: =IF(OR('1. Entrada'!V16="",'1. Entrada'!W16=""),"",'1. Entrada'!V16-'1. Entrada'!W16)
A17: ='1. Entrada'!A17 | B17: =IFERROR(('1. Entrada'!B17-'1. Entrada'!H17)/'1. Entrada'!B17,"") | C17: =IFERROR(('1. Entrada'!C17-'1. Entrada'!I17)/'1. Entrada'!C17,"") | D17: =IFERROR(('1. Entrada'!D17-'1. Entrada'!J17)/'1. Entrada'!D17,"") | E17: =IFERROR(('1. Entrada'!E17-'1. Entrada'!K17)/'1. Entrada'!E17,"") | F17: =IFERROR(('1. Entrada'!F17-'1. Entrada'!L17)/'1. Entrada'!F17,"") | G17: =IFERROR(('1. Entrada'!G17-'1. Entrada'!M17)/'1. Entrada'!G17,"") | H17: =IFERROR('1. Entrada'!B17/(SUM('1. Entrada'!B17:G17)),"") | I17: =IFERROR('1. Entrada'!C17/(SUM('1. Entrada'!B17:G17)),"") | J17: =IFERROR('1. Entrada'!D17/(SUM('1. Entrada'!B17:G17)),"") | K17: =IFERROR('1. Entrada'!E17/(SUM('1. Entrada'!B17:G17)),"") | L17: =IFERROR('1. Entrada'!F17/(SUM('1. Entrada'!B17:G17)),"") | M17: =IFERROR('1. Entrada'!G17/(SUM('1. Entrada'!B17:G17)),"") | N17: =IFERROR(((SUM('1. Entrada'!B17:G17))-(SUM('1. Entrada'!H17:M17)))/(SUM('1. Entrada'!B17:G17)),"") | O17: =IFERROR('1. Entrada'!N17/((SUM('1. Entrada'!B17:G17))-(SUM('1. Entrada'!H17:M17))),"") | P17: =IFERROR('1. Entrada'!P17/'1. Entrada'!H17*30,"") | Q17: =IFERROR('1. Entrada'!Q17/'1. Entrada'!I17*30,"") | R17: =IFERROR('1. Entrada'!R17/'1. Entrada'!J17*30,"") | S17: =IFERROR('1. Entrada'!S17/'1. Entrada'!K17*30,"") | T17: =IFERROR('1. Entrada'!T17/'1. Entrada'!L17*30,"") | U17: =IFERROR('1. Entrada'!U17/'1. Entrada'!M17*30,"") | V17: =IFERROR((SUM('1. Entrada'!P17:U17))/(SUM('1. Entrada'!H17:M17))*30,"") | W17: =IFERROR('1. Entrada'!O17/(((SUM('1. Entrada'!B17:G17))-(SUM('1. Entrada'!H17:M17)))/(SUM('1. Entrada'!B17:G17))),"") | X17: =IF(OR('1. Entrada'!V17="",'1. Entrada'!W17=""),"",'1. Entrada'!V17-'1. Entrada'!W17)
A19: Peso y cobertura de stock no llevan semáforo: no hay un "mejor" único (una familia puede pesar poco a propósito, y algo de cobertura es sano). Léelos en la hoja "4. Cómo se lee".

Sheet 3. Tendencia
A1: TENDENCIA · LOS CINCO RATIOS MES A MES
A2: Se dibuja solo desde "2. Ratios". Un ratio suelto no dice gran cosa; tres meses seguidos dicen casi todo. Eje izquierdo: porcentajes y días. Eje derecho: punto muerto en euros.
A27: Qué es cada línea: margen bruto global (%) · coste de personal sobre margen bruto (%) · cobertura de stock global (días) · desfase de caja (días) · punto muerto del mes (€, eje derecho). El detalle por familia de margen y cobertura está en la hoja "2. Ratios": no cabe en un solo gráfico legible junto a los otros tres ratios.

Sheet 4. Cómo se lee
A1: CÓMO SE LEE CADA RATIO
A2: Compara tu farmacia consigo misma, nunca con un "sector" que nadie audita. Cada bloque dice qué mirar y qué decisión concreta abre.
B4: Regla general: nada de benchmarks de fuera
B5: Ningún número de esta hoja se compara con una media de sector, porque nadie la audita y varía por tamaño, ubicación y mezcla de familias. El semáforo de "2. Ratios" compara cada mes con tus propios últimos doce: verde es mejor que tus otros meses, rojo es peor.
B6: Con menos de 3-4 meses cargados el semáforo no dice mucho todavía. Empieza a ser útil a partir del tercer o cuarto mes, cuando ya hay con qué compararse.
B8: 1. Margen bruto por familia y su peso
B9: Qué mirar: una familia cuyo peso en ventas se mantiene o sube mientras su margen cae respecto a tus propios meses anteriores. O una familia pequeña con margen alto a la que no le dedicas mostrador ni acción comercial desde hace tiempo.
B10: Decisión que abre: mover escaparate, formación del equipo y condiciones de compra hacia la familia que sí devuelve margen, y dejar de comprar solo por la condición del laboratorio.
B12: 2. Coste de personal sobre el margen bruto (no sobre las ventas)
B13: Qué mirar: si este porcentaje sube mes a mes respecto a tu propia serie, sobre todo justo después de una incorporación o de una caída de margen en el ratio 1.
B14: Decisión que abre: casi nunca es recortar plantilla. Es revisar qué vende cada persona, qué familias domina y qué le falta para recomendar con criterio lo que hoy pasa de largo por el mostrador.
B16: 3. Cobertura de stock en días, por familia
B17: Qué mirar: una familia cuya cobertura se dispara varios meses seguidos frente a tu propia media, sobre todo si viene de una condición de compra reciente. La cobertura global sirve para el vistazo rápido; la decisión real se toma familia a familia.
B18: Decisión que abre: frenar el pedido de esa familia y, si la condición de compra fue lo que disparó la cobertura, hacer cuentas de si el descuento compensa el dinero parado. A menudo no compensa.
... B33: farmapro · farmapro.es
